README.txt
TODO.txt
setup.py
p4a/__init__.py
p4a.image.egg-info/PKG-INFO
p4a.image.egg-info/SOURCES.txt
p4a.image.egg-info/dependency_links.txt
p4a.image.egg-info/entry_points.txt
p4a.image.egg-info/namespace_packages.txt
p4a.image.egg-info/not-zip-safe
p4a.image.egg-info/requires.txt
p4a.image.egg-info/top_level.txt
p4a/image/__init__.py
p4a/image/configure.zcml
p4a/image/imageanno.py
p4a/image/interfaces.py
p4a/image/media.py
p4a/image/migration.py
p4a/image/migration.txt
p4a/image/subtype.py
p4a/image/utils.py
p4a/image/validation.py
p4a/image/browser/__init__.py
p4a/image/browser/col_playlist.pt
p4a/image/browser/configure.zcml
p4a/image/browser/displays.py
p4a/image/browser/image-container.pt
p4a/image/browser/image.pt
p4a/image/browser/image.py
p4a/image/browser/imagecol-popup.pt
p4a/image/browser/media.py
p4a/image/browser/support.py
p4a/image/browser/widget.py
p4a/image/browser/resources/imagestyles/image.css
p4a/image/docs/TODO.txt
p4a/image/locales/plone4artistsimage.pot
p4a/image/locales/ja/LC_MESSAGES/plone4artists.mo
p4a/image/locales/ja/LC_MESSAGES/plone4artists.po
p4a/image/locales/pt/LC_MESSAGES/plone4artists.mo
p4a/image/locales/pt/LC_MESSAGES/plone4artists.po
p4a/image/locales/pt_BR/LC_MESSAGES/plone4artists.mo
p4a/image/locales/pt_BR/LC_MESSAGES/plone4artists.po
p4a/image/tests/__init__.py
p4a/image/tests/extraction.txt
p4a/image/tests/test_docunittests.py
p4a/image/tests/samples/USS_Constitution.jpg
p4a/image/tests/samples/generic.ai
p4a/image/tests/samples/gif_test.gif
p4a/image/tests/samples/no_metadata.jpg
p4a/image/thirdparty/EXIF.py
p4a/image/thirdparty/__init__.py
p4a/image/thirdparty/_imagedata.py
p4a/image/thirdparty/configure.zcml
p4a/image/thirdparty/iptcinfo.py