Metadata-Version: 1.0
Name: p4a.image
Version: 0.2
Summary: UNKNOWN
Home-page: http://svn.plone.org/svn/plone/plone.example
Author: David Siedband
Author-email: technique@oceanicsky.com
License: GPL
Platform: UNKNOWN
